playwright_interceptor/__init__.py
playwright_interceptor/content_loader.py
playwright_interceptor/execute.py
playwright_interceptor/handler.py
playwright_interceptor/models.py
playwright_interceptor/network_interceptor.py
playwright_interceptor/request_interceptor.py
playwright_interceptor/tools.py
playwright_interceptor/config/__init__.py
playwright_interceptor/config/errors.py
playwright_interceptor/config/logs.py
playwright_interceptor/config/network.py
playwright_interceptor/config/parameters.py
playwright_interceptor-0.1.1.dist-info/licenses/LICENSE
playwright_interceptor-0.1.1.dist-info/METADATA
playwright_interceptor-0.1.1.dist-info/WHEEL
playwright_interceptor-0.1.1.dist-info/top_level.txt
playwright_interceptor-0.1.1.dist-info/RECORD
