Metadata-Version: 2.4
Name: playwright_interceptor
Version: 0.1.1
Summary: Addon for Playwright for intercepting and modifying HTTP requests and responses.
Author: Miskler
License: MIT
Project-URL: Homepage, https://github.com/Open-Inflation/playwright_interceptor
Classifier: Programming Language :: Python :: 3
Classifier: Programming Language :: Python :: 3.10
Classifier: Programming Language :: Python :: 3.11
Classifier: Programming Language :: Python :: 3.12
Classifier: Programming Language :: Python :: 3.13
Classifier: License :: OSI Approved :: MIT License
Classifier: Operating System :: Microsoft :: Windows
Classifier: Operating System :: POSIX :: Linux
Classifier: Intended Audience :: Developers
Classifier: Intended Audience :: Information Technology
Classifier: Topic :: Software Development :: Libraries :: Python Modules
Classifier: Topic :: Internet
Classifier: Topic :: Utilities
Requires-Python: >=3.10
License-File: LICENSE
Requires-Dist: playwright
Requires-Dist: beartype
Dynamic: license-file
